{
  "id": "5",
  "title": "Lớp 12 luyện thi THPT Quốc Gia 8+",
  "desc": "Chương trình luyện thi toàn diện trọng tâm Toán 12, bao quát 100% dạng bài thi tốt nghiệp THPT.",
  "teacher": "Thầy Hoàng Triều",
  "duration": "50 giờ",
  "totalLessons": 40,
  "progress": 0,
  "sections": [
    {
      "id": "c12-sec1",
      "title": "Chương 1: Ứng dụng Đạo hàm khảo sát đồ thị hàm số",
      "duration": "160 phút",
      "items": [
        {
          "id": "c12-f1",
          "title": "Bài 1: Sự đồng biến, nghịch biến của hàm số",
          "duration": "35 phút",
          "type": "video",
          "url": "https://www.youtube.com/embed/dQw4w9WgXcQ"
        },
        {
          "id": "c12-f2",
          "title": "Bài 2: Cực trị của hàm số và các dạng bài tham số m",
          "duration": "40 phút",
          "type": "video",
          "url": "https://www.youtube.com/embed/dQw4w9WgXcQ"
        },
        {
          "id": "c12-f3",
          "title": "Bài 3: Giá trị lớn nhất, nhỏ nhất trên đoạn",
          "duration": "30 phút",
          "type": "video",
          "url": "https://www.youtube.com/embed/dQw4w9WgXcQ"
        },
        {
          "id": "c12-f4",
          "title": "Tuyển tập 500 bài tập Hàm số trích từ đề thi thật",
          "duration": "50 trang",
          "type": "pdf",
          "url": "https://pdfobject.com/pdf/sample.pdf"
        }
      ]
    },
    {
      "id": "c12-sec2",
      "title": "Chương 2: Nguyên hàm, Tích phân & Ứng dụng",
      "duration": "150 phút",
      "items": [
        {
          "id": "c12-f5",
          "title": "Bài 1: Bảng nguyên hàm cơ bản và phương pháp đổi biến",
          "duration": "40 phút",
          "type": "video",
          "url": "https://www.youtube.com/embed/dQw4w9WgXcQ"
        },
        {
          "id": "c12-f6",
          "title": "Bài 2: Tích phân từng phần và ứng dụng tính diện tích",
          "duration": "45 phút",
          "type": "video",
          "url": "https://www.youtube.com/embed/dQw4w9WgXcQ"
        },
        {
          "id": "c12-f7",
          "title": "Đề thi thử chuyên đề Tích phân chuẩn cấu trúc BGD",
          "duration": "20 trang",
          "type": "pdf",
          "url": "https://pdfobject.com/pdf/sample.pdf"
        }
      ]
    }
  ]
}